gitcg/__init__.py
gitcg/_gitcg_cffi.py
gitcg/create_param.py
gitcg/entity.py
gitcg/env.py
gitcg/game.py
gitcg/libgitcg.dylib
gitcg/low_level.py
gitcg/player.py
gitcg/state.py
gitcg/proto/__init__.py
gitcg/proto/action_pb2.py
gitcg/proto/action_pb2.pyi
gitcg/proto/enums_pb2.py
gitcg/proto/enums_pb2.pyi
gitcg/proto/mutation_pb2.py
gitcg/proto/mutation_pb2.pyi
gitcg/proto/notification_pb2.py
gitcg/proto/notification_pb2.pyi
gitcg/proto/preview_pb2.py
gitcg/proto/preview_pb2.pyi
gitcg/proto/rpc_pb2.py
gitcg/proto/rpc_pb2.pyi
gitcg/proto/state_pb2.py
gitcg/proto/state_pb2.pyi
gitcg-0.17.4.dist-info/METADATA
gitcg-0.17.4.dist-info/WHEEL
gitcg-0.17.4.dist-info/RECORD
