Metadata-Version: 2.4
Name: gitcg
Version: 0.17.4
Summary: Genius Invokation TCG (Python binding)
Author-email: guyutongxue <guyutongxue@163.com>
Requires-Python: >=3.11
Requires-Dist: cffi>=1.17.1
Requires-Dist: protobuf>=5.29.1
